shangjian_api/__init__.py
shangjian_api/exceptions.py
shangjian_api/settings.py
shangjian_api/airworks/__init__.py
shangjian_api/airworks/base_api.py
shangjian_api/airworks/package_api.py
shangjian_api/airworks/settings.py
shangjian_api/km/__init__.py
shangjian_api/km/base_api.py
shangjian_api/km/settings.py
shangjian_api-0.0.6.dist-info/METADATA
shangjian_api-0.0.6.dist-info/WHEEL
shangjian_api-0.0.6.dist-info/top_level.txt
shangjian_api-0.0.6.dist-info/RECORD
