Metadata-Version: 2.1
Name: shangjian_api
Version: 0.0.6
Summary: Tool for shangjian sdk
Author: valuesimplex
Classifier: Development Status :: 3 - Alpha
Classifier: Intended Audience :: Developers
Classifier: Topic :: Software Development :: Build Tools
Classifier: License :: OSI Approved :: MIT License
Classifier: Programming Language :: Python :: 3
Requires-Python: >=3.5
Requires-Dist: pandas
Requires-Dist: requests
Requires-Dist: toml
